graphene_django_crud/__init__.py
graphene_django_crud/base_types.py
graphene_django_crud/converter.py
graphene_django_crud/fields.py
graphene_django_crud/input_types.py
graphene_django_crud/registry.py
graphene_django_crud/settings.py
graphene_django_crud/types.py
graphene_django_crud/utils.py
old/__init__.py
old/apps.py
old/client.py
old/conftest.py
old/models.py
old/schema.py
old/signals.py
old/urls.py
old/utils.py
old/choices_converter/__init__.py
old/choices_converter/models.py
old/choices_converter/schema.py
old/connection/__init__.py
old/connection/models.py
old/connection/schema.py
old/connection/test_main.py
old/djangocontribauth/__init__.py
old/djangocontribauth/schema.py
old/djangocontribauth/signal.py
old/djangocontribauth/test_main.py
old/file_field/__init__.py
old/file_field/http_multipart.py
old/file_field/models.py
old/file_field/schema.py
old/file_field/test_main.py
old/issues/__init__.py
old/issues/models.py
old/issues/schema.py
old/issues/test_issue_8.py
old/migrations/0001_initial.py
old/migrations/0002_alter_testfkb_testfkc.py
old/migrations/0002_testrelaya_testrelayb.py
old/migrations/0003_alter_testo2ob_testo2oc.py
old/migrations/0004_merge_20210510_1402.py
old/migrations/0005_testconna_testconnb_testconnc.py
old/migrations/0006_auto_20210528_0708.py
old/migrations/0007_auto_20210528_0753.py
old/migrations/0008_issue8.py
old/migrations/__init__.py
old/relationship/__init__.py
old/relationship/models.py
old/relationship/schema.py
old/relationship/test_main.py
old/relationship/test_self_relation.py
old/relay/__init__.py
old/relay/models.py
old/relay/schema.py
old/relay/test_main.py
tests/__init__.py
tests/apps.py
tests/client.py
tests/models.py
tests/rundevserver.py
tests/schema.py
tests/signals.py
tests/test_settings.py
tests/urls.py
tests/utils.py
tests/choices_converter/__init__.py
tests/choices_converter/models.py
tests/choices_converter/schema.py
tests/connection/__init__.py
tests/connection/models.py
tests/connection/schema.py
graphene_django_crud-2.0.0.dist-info/LICENSE
graphene_django_crud-2.0.0.dist-info/METADATA
graphene_django_crud-2.0.0.dist-info/WHEEL
graphene_django_crud-2.0.0.dist-info/top_level.txt
graphene_django_crud-2.0.0.dist-info/RECORD
