Metadata-Version: 2.1
Name: graphene-django-crud
Version: 2.0.0
Summary: Turns the django ORM into a graphql API
Home-page: https://github.com/djipidi/graphene_django_crud
Author: djipidi
Author-email: djipidi.dev@gmail.com
Classifier: Programming Language :: Python :: 3
Classifier: License :: OSI Approved :: MIT License
Classifier: Operating System :: OS Independent
Requires-Python: >=3.6
License-File: LICENSE
Requires-Dist: Django (>=3.2)
Requires-Dist: graphene (<4,>=3.0)
Requires-Dist: graphene-django (<4,>=3.0)
